autogui/__init__.py
autogui/aiclient.py
autogui/aicodegen.py
autogui/example_image_editor.py
autogui/example_stock.py
autogui/providers.json
autogui/schema.py
autogui/settings.py
autogui/frontend/build/bootstrap.min.css
autogui/frontend/build/index.html
autogui/frontend/build/assets/index-BHqyUzrZ.js
autogui/frontend/build/assets/index-CI7-TZBE.js
build/lib/autogui/__init__.py
build/lib/autogui/aiclient.py
build/lib/autogui/aicodegen.py
build/lib/autogui/example_image_editor.py
build/lib/autogui/example_stock.py
build/lib/autogui/schema.py
build/lib/autogui/settings.py
build/lib/build/lib/autogui/__init__.py
build/lib/build/lib/autogui/aiclient.py
build/lib/build/lib/autogui/aicodegen.py
build/lib/build/lib/autogui/example_image_editor.py
build/lib/build/lib/autogui/example_stock.py
build/lib/build/lib/autogui/schema.py
build/lib/build/lib/autogui/settings.py
build/lib/build/lib/build/lib/autogui/__init__.py
build/lib/build/lib/build/lib/autogui/aiclient.py
build/lib/build/lib/build/lib/autogui/aicodegen.py
build/lib/build/lib/build/lib/autogui/example_image_editor.py
build/lib/build/lib/build/lib/autogui/example_stock.py
build/lib/build/lib/build/lib/autogui/schema.py
build/lib/build/lib/build/lib/autogui/settings.py
build/lib/build/lib/build/lib/build/lib/autogui/__init__.py
build/lib/build/lib/build/lib/build/lib/autogui/aiclient.py
build/lib/build/lib/build/lib/build/lib/autogui/aicodegen.py
build/lib/build/lib/build/lib/build/lib/autogui/example_image_editor.py
build/lib/build/lib/build/lib/build/lib/autogui/example_stock.py
build/lib/build/lib/build/lib/build/lib/autogui/schema.py
build/lib/build/lib/build/lib/build/lib/autogui/settings.py
build/lib/build/lib/build/lib/build/lib/build/lib/autogui/__init__.py
build/lib/build/lib/build/lib/build/lib/build/lib/autogui/aiclient.py
build/lib/build/lib/build/lib/build/lib/build/lib/autogui/aicodegen.py
build/lib/build/lib/build/lib/build/lib/build/lib/autogui/example_image_editor.py
streamlit_autogui-0.0.4.dist-info/licenses/LICENSE
streamlit_autogui-0.0.4.dist-info/METADATA
streamlit_autogui-0.0.4.dist-info/WHEEL
streamlit_autogui-0.0.4.dist-info/top_level.txt
streamlit_autogui-0.0.4.dist-info/RECORD
